rym/lpath/__about__.py
rym/lpath/__init__.py
rym/lpath/_delim.py
rym/lpath/_get.py
rym/lpath/_remove.py
rym/lpath/_set.py
rym_lpath-0.4.1.dist-info/METADATA
rym_lpath-0.4.1.dist-info/WHEEL
rym_lpath-0.4.1.dist-info/RECORD
