Metadata-Version: 2.4
Name: rym-lpath
Version: 0.4.1
Summary: A python library for accessing mappings and objects.
Project-URL: Homepage, https://github.com/muppetjones/rym-py/tree/main/rym-lpath
Project-URL: Bug Tracker, https://github.com/muppetjones/rym-py/issues
Project-URL: Documentation, https://muppetjones.github.io/rym-py/rym-lpath
Author-email: Stephen Bush <2041619+muppetjones@users.noreply.github.com>
License: MIT
Classifier: License :: OSI Approved :: MIT License
Classifier: Operating System :: OS Independent
Classifier: Programming Language :: Python :: 3
Requires-Python: >=3.8
